scrapy_rabbitmq_scheduler/__init__.py
scrapy_rabbitmq_scheduler/connection.py
scrapy_rabbitmq_scheduler/middleware.py
scrapy_rabbitmq_scheduler/picklecompat.py
scrapy_rabbitmq_scheduler/pipelines.py
scrapy_rabbitmq_scheduler/queue.py
scrapy_rabbitmq_scheduler/scheduler.py
scrapy_rabbitmq_scheduler/spiders.py
scrapy_rabbitmq_task-1.0.4.dist-info/METADATA
scrapy_rabbitmq_task-1.0.4.dist-info/WHEEL
scrapy_rabbitmq_task-1.0.4.dist-info/top_level.txt
scrapy_rabbitmq_task-1.0.4.dist-info/RECORD
