Metadata-Version: 2.1
Name: scrapy_rabbitmq_task
Version: 1.0.4
Summary: Rabbitmq for Distributed scraping
Home-page: https://gitee.com/tieyongjie/scrapy-mq
Author: white.tie
Author-email: 1042798703@qq.com
License: MIT
Requires-Dist: pika
